qcdb/__init__.py
qcdb/cli.py
qcdb/core.py
qcdb/vault.py
qcdb-0.2.1.dist-info/METADATA
qcdb-0.2.1.dist-info/WHEEL
qcdb-0.2.1.dist-info/entry_points.txt
qcdb-0.2.1.dist-info/licenses/LICENSE
qcdb-0.2.1.dist-info/RECORD
