Metadata-Version: 2.4
Name: qcdb
Version: 0.2.1
Summary: Knowledge management app to interface with quantum chemical calculations
Project-URL: Repository, https://codeberg.org/crabby/qcdb
License-Expression: MIT
License-File: LICENSE
Requires-Python: >=3.11
Requires-Dist: orca-studio>=0.2.16
Requires-Dist: typer>=0.16.1
